aiptrms/__init__.py
aiptrms/main.py
aiptrms/ptrms_extractor.py
aiptrms-0.1.11.dist-info/WHEEL
aiptrms-0.1.11.dist-info/METADATA
aiptrms-0.1.11.dist-info/RECORD
