Metadata-Version: 2.1
Name: aiptrms
Version: 0.1.11
Summary: 
Author: mjaquier
Author-email: mjaquier@mjaquier.xyz
Requires-Python: >=3.8,<4.0
Classifier: Programming Language :: Python :: 3
Classifier: Programming Language :: Python :: 3.8
Requires-Dist: aihelper (>=0.2.8,<0.3.0)
Requires-Dist: numpy (>=1.19.3,<2.0.0)
Requires-Dist: openpyxl (>=3.0.5,<4.0.0)
Requires-Dist: pandas (>=1.1.3,<2.0.0)
Requires-Dist: xlrd (>=1.2.0,<2.0.0)
